ranger21/__init__.py
ranger21/chebyshev_lr_functions.py
ranger21/ranger21.py
ranger21/rangerabel.py
ranger21-0.1.0.dist-info/LICENSE
ranger21-0.1.0.dist-info/METADATA
ranger21-0.1.0.dist-info/WHEEL
ranger21-0.1.0.dist-info/RECORD
