Metadata-Version: 2.1
Name: ranger21
Version: 0.1.0
Summary: A rewrite of the Ranger deep learning optimizer to integrate newer optimization ideas
License: Apache-2.0
Author: Less Wright
Author-email: lessw@etrillium.com
Requires-Python: >=3.10,<4.0
Classifier: License :: OSI Approved :: Apache Software License
Classifier: Programming Language :: Python :: 3
Classifier: Programming Language :: Python :: 3.10
Classifier: Programming Language :: Python :: 3.11
Requires-Dist: matplotlib
Requires-Dist: numpy
Requires-Dist: torch
